mfd_cli_client/__init__.py
mfd_cli_client/base.py
mfd_cli_client/exceptions.py
mfd_cli_client-1.11.0.dist-info/licenses/AUTHORS.md
mfd_cli_client-1.11.0.dist-info/licenses/LICENSE.md
mfd_cli_client-1.11.0.dist-info/METADATA
mfd_cli_client-1.11.0.dist-info/WHEEL
mfd_cli_client-1.11.0.dist-info/top_level.txt
mfd_cli_client-1.11.0.dist-info/RECORD
