Metadata-Version: 2.4
Name: mfd-cli-client
Version: 1.11.0
Summary: Module for cli_client (command line interface client) utility for the Intel® Infrastructure Processing Unit (Intel® IPU).
Project-URL: Homepage, https://github.com/intel/mfd
Project-URL: Repository, https://github.com/intel/mfd-cli-client
Project-URL: Issues, https://github.com/intel/mfd-cli-client/issues
Project-URL: Changelog, https://github.com/intel/mfd-cli-client/blob/main/CHANGELOG.md
Requires-Python: <3.14,>=3.10
License-File: LICENSE.md
License-File: AUTHORS.md
Requires-Dist: mfd-typing>=1.23.0
Requires-Dist: mfd-base-tool>=2.7.0
Dynamic: license-file
